bluecanary/__init__.py
bluecanary/__main__.py
bluecanary/exceptions.py
bluecanary/set_cloudwatch_alarm.py
bluecanary/builtin_plugins/disk_utilization.py
bluecanary/builtin_plugins/memory_utilization.py
bluecanary/managers/__init__.py
bluecanary/managers/alarms_manager.py
bluecanary/managers/aws_credentials_manager.py
bluecanary/managers/configuration_manager.py
bluecanary/managers/tags_manager.py
bluecanary/plugins/__init__.py
bluecanary/plugins/load_plugins.py
bluecanary/plugins/plugin_base_class.py
bluecanary/scripts/__init__.py
bluecanary/scripts/bluecanary.py
bluecanary/scripts/update_alarms/__init__.py
bluecanary/scripts/update_alarms/update_ec2_alarms.py
bluecanary/scripts/update_alarms/update_elb_alarms.py
bluecanary/scripts/update_tags/__init__.py
bluecanary/scripts/update_tags/update_ec2_tags.py
bluecanary/scripts/update_tags/update_elb_tags.py
bluecanary/tags/__init__.py
bluecanary/tags/ec2.py
bluecanary/tags/elb.py
bluecanary/tests/__init__.py
bluecanary/tests/test_set_cloudwatch_alarm.py
bluecanary/tests/managers/__init__.py
bluecanary/tests/managers/test_alarms_manager.py
bluecanary/tests/managers/test_aws_credentials_manager.py
bluecanary/tests/managers/test_configuration_manager.py
bluecanary/tests/managers/test_tags_manager.py
bluecanary/tests/plugins/__init__.py
bluecanary/tests/plugins/test_load_plugins.py
bluecanary/tests/tags/__init__.py
bluecanary/tests/tags/test_ec2_tags.py
bluecanary/tests/tags/test_elb_tags.py
bluecanary/tests/utilities/__init__.py
bluecanary/tests/utilities/test_load_yaml.py
bluecanary/tests/utilities/test_throttle.py
bluecanary/utilities/__init__.py
bluecanary/utilities/credentials_decorator.py
bluecanary/utilities/load_yaml.py
bluecanary/utilities/throttle_decorator.py
bluecanary-0.0.7.dist-info/DESCRIPTION.rst
bluecanary-0.0.7.dist-info/entry_points.txt
bluecanary-0.0.7.dist-info/METADATA
bluecanary-0.0.7.dist-info/metadata.json
bluecanary-0.0.7.dist-info/RECORD
bluecanary-0.0.7.dist-info/top_level.txt
bluecanary-0.0.7.dist-info/WHEEL
