Metadata-Version: 2.0
Name: bluecanary
Version: 0.0.7
Summary: UNKNOWN
Home-page: UNKNOWN
Author: UNKNOWN
Author-email: UNKNOWN
License: UNKNOWN
Platform: UNKNOWN
Requires-Dist: boto3 (==1.2.3)
Requires-Dist: click (==6.2)
Requires-Dist: pluginbase (==0.3)
Requires-Dist: PyYAML (==3.11)
